cologne_phonetics.py
cologne_phonetics-2.0.0.dist-info/LICENSE.txt
cologne_phonetics-2.0.0.dist-info/METADATA
cologne_phonetics-2.0.0.dist-info/WHEEL
cologne_phonetics-2.0.0.dist-info/RECORD
