Metadata-Version: 2.1
Name: cologne_phonetics
Version: 2.0.0
Summary: Python implementation of the cologne-phonetics algorithm
License: MIT
Author: Janek Nouvertné
Requires-Python: >=3.8
Classifier: License :: OSI Approved :: MIT License
Classifier: Programming Language :: Python :: 3
Classifier: Programming Language :: Python :: 3.8
Classifier: Programming Language :: Python :: 3.9
Classifier: Programming Language :: Python :: 3.10
Classifier: Programming Language :: Python :: 3.11
Classifier: Programming Language :: Python :: 3.12
